<billhistory bill="85(R) HB 4028" lastUpdate="3/16/2017 2:00:44 AM" source="Texas Legislature Online website (ftp://ftp.legis.state.tx.us) - Texas Legislative Council" disclaimer="The Texas Legislative Council makes no representation as to the completeness, timeliness, or accuracy of this data and makes no warranty in regard to its use." xmlns=""><lastaction>03/10/2017 H Filed</lastaction><caption version="Introduced">Relating to the issuance of a transportation network company driver's license; requiring an occupational license; authorizing a fee; providing a civil penalty.</caption><authors>Rodriguez, Eddie</authors><coauthors /><sponsors /><cosponsors /><subjects><subject>Vehicles &amp; Traffic--Driver's Licenses (I0840)</subject><subject>OCCUPATIONAL DRIVER'S LICENSE (S0699)</subject><subject>VEHICLES FOR HIRE (S0795)</subject><subject>MOTOR VEHICLES, TEXAS DEPARTMENT OF (V0812)</subject></subjects><companions>SB 748 by Zaffirini, Identical </companions><enablinglegislation /><committees><house name="" status="" ayeVotes="0" nayVotes="0" presentNotVotingVotes="0" absentVotes="0" subcommitteeName="" subcommitteeStatus="" /><senate name="" status="" ayeVotes="0" nayVotes="0" presentNotVotingVotes="0" absentVotes="0" subcommitteeName="" subcommitteeStatus="" /></committees><conferees><house /><senate /></conferees><actions><action><actionNumber>H001</actionNumber><date>3/10/2017</date><description>Filed</description><comment /><actionTimestamp /></action></actions><billtext><docTypes><bill><versions><version><versionDescription>Introduced</versionDescription><WebHTMLURL>http://www.legis.state.tx.us/tlodocs/85R/billtext/html/HB04028I.HTM</WebHTMLURL><WebPDFURL>http://www.legis.state.tx.us/tlodocs/85R/billtext/pdf/HB04028I.PDF</WebPDFURL><FTPHTMLURL>ftp://ftp.legis.state.tx.us/bills/85R/billtext/HTML/house_bills/HB04000_HB04099/HB04028I.HTM</FTPHTMLURL><FTPPDFURL>ftp://ftp.legis.state.tx.us/bills/85R/billtext/PDF/house_bills/HB04000_HB04099/HB04028I.PDF</FTPPDFURL></version></versions></bill><analysis><versions /></analysis><fiscalNote><versions /></fiscalNote></docTypes></billtext></billhistory>