<billhistory bill="84(R) HB 2893" lastUpdate="5/16/2015 2:00:21 AM" source="Texas Legislature Online website (ftp://ftp.legis.state.tx.us) - Texas Legislative Council" disclaimer="The Texas Legislative Council makes no representation as to the completeness, timeliness, or accuracy of this data and makes no warranty in regard to its use." xmlns=""><lastaction>05/14/2015 H Laid on the table subject to call</lastaction><caption version="House Committee Report">Relating to the licensing of insurance agents and adjusters; providing a penalty.</caption><authors>Frullo</authors><coauthors /><sponsors /><cosponsors /><subjects><subject>Insurance--Insurers &amp; Agents (I0425)</subject><subject>Occupational Regulation--Other Trades &amp; Professions (I0541)</subject><subject>CONTINUING EDUCATION (S0234)</subject><subject>INSURANCE ADJUSTERS (S0539)</subject><subject>INSURANCE, COMMISSIONER OF (V0396)</subject><subject>INSURANCE, TEXAS DEPARTMENT OF (V0006)</subject></subjects><companions>SB 876 by Eltife, Identical </companions><enablinglegislation /><committees><house name="Insurance" status="Out of committee" ayeVotes="7" nayVotes="0" presentNotVotingVotes="0" absentVotes="2" subcommitteeName="" subcommitteeStatus="" /><senate name="" status="" ayeVotes="0" nayVotes="0" presentNotVotingVotes="0" absentVotes="0" subcommitteeName="" subcommitteeStatus="" /></committees><conferees><house /><senate /></conferees><actions><action><actionNumber>H001</actionNumber><date>3/10/2015</date><description>Filed</description><comment /><actionTimestamp /></action><action><actionNumber>H005</actionNumber><date>3/16/2015</date><description>Read first time</description><comment /><actionTimestamp /></action><action><actionNumber>H085</actionNumber><date>3/16/2015</date><description>Referred to Insurance</description><comment /><actionTimestamp>3/16/2015 4:36:00 PM</actionTimestamp></action><action><actionNumber>H228</actionNumber><date>5/6/2015</date><description>Scheduled for public hearing on . . .</description><comment /><actionTimestamp /></action><action><actionNumber>H215</actionNumber><date>5/6/2015</date><description>Considered in public hearing</description><comment /><actionTimestamp /></action><action><actionNumber>H240</actionNumber><date>5/6/2015</date><description>Testimony taken/registration(s) recorded in committee</description><comment /><actionTimestamp /></action><action><actionNumber>H250</actionNumber><date>5/6/2015</date><description>Reported favorably w/o amendment(s)</description><comment /><actionTimestamp /></action><action><actionNumber>H853</actionNumber><date>5/7/2015</date><description>Comte report filed with Committee Coordinator</description><comment /><actionTimestamp /></action><action><actionNumber>H855</actionNumber><date>5/7/2015</date><description>Committee report distributed</description><comment /><actionTimestamp>5/7/2015 3:03:00 PM</actionTimestamp></action><action><actionNumber>H400</actionNumber><date>5/7/2015</date><description>Committee report sent to Calendars</description><comment /><actionTimestamp /></action><action><actionNumber>H415</actionNumber><date>5/8/2015</date><description>Considered in Calendars</description><comment /><actionTimestamp /></action><action><actionNumber>H435</actionNumber><date>5/11/2015</date><description>Placed on General State Calendar</description><comment /><actionTimestamp /></action><action><actionNumber>H506</actionNumber><date>5/14/2015</date><description>Companion considered in lieu of</description><comment>SB 876</comment><actionTimestamp /></action><action><actionNumber>H621</actionNumber><date>5/14/2015</date><description>Laid on the table subject to call</description><comment /><actionTimestamp /></action></actions><billtext><docTypes><bill><versions><version><versionDescription>Introduced</versionDescription><WebHTMLURL>http://www.legis.state.tx.us/tlodocs/84R/billtext/html/HB02893I.HTM</WebHTMLURL><WebPDFURL>http://www.legis.state.tx.us/tlodocs/84R/billtext/pdf/HB02893I.PDF</WebPDFURL><FTPHTMLURL>ftp://ftp.legis.state.tx.us/bills/84R/billtext/HTML/house_bills/HB02800_HB02899/HB02893I.HTM</FTPHTMLURL><FTPPDFURL>ftp://ftp.legis.state.tx.us/bills/84R/billtext/PDF/house_bills/HB02800_HB02899/HB02893I.PDF</FTPPDFURL></version><version><versionDescription>House Committee Report</versionDescription><WebHTMLURL>http://www.legis.state.tx.us/tlodocs/84R/billtext/html/HB02893H.HTM</WebHTMLURL><WebPDFURL>http://www.legis.state.tx.us/tlodocs/84R/billtext/pdf/HB02893H.PDF</WebPDFURL><FTPHTMLURL>ftp://ftp.legis.state.tx.us/bills/84R/billtext/HTML/house_bills/HB02800_HB02899/HB02893H.HTM</FTPHTMLURL><FTPPDFURL>ftp://ftp.legis.state.tx.us/bills/84R/billtext/PDF/house_bills/HB02800_HB02899/HB02893H.PDF</FTPPDFURL></version></versions></bill><analysis><versions><version><versionDescription>House Committee Report</versionDescription><WebHTMLURL>http://www.legis.state.tx.us/tlodocs/84R/analysis/html/HB02893H.HTM</WebHTMLURL><WebPDFURL>http://www.legis.state.tx.us/tlodocs/84R/analysis/pdf/HB02893H.PDF</WebPDFURL><FTPHTMLURL>ftp://ftp.legis.state.tx.us/bills/84R/analysis/HTML/house_bills/HB02800_HB02899/HB02893H.HTM</FTPHTMLURL><FTPPDFURL>ftp://ftp.legis.state.tx.us/bills/84R/analysis/PDF/house_bills/HB02800_HB02899/HB02893H.PDF</FTPPDFURL></version></versions></analysis><fiscalNote><versions><version><versionDescription>Introduced</versionDescription><WebHTMLURL>http://www.legis.state.tx.us/tlodocs/84R/fiscalNotes/html/HB02893I.HTM</WebHTMLURL><WebPDFURL>http://www.legis.state.tx.us/tlodocs/84R/fiscalNotes/pdf/HB02893I.PDF</WebPDFURL><FTPHTMLURL>ftp://ftp.legis.state.tx.us/bills/84R/fiscalNotes/HTML/house_bills/HB02800_HB02899/HB02893I.HTM</FTPHTMLURL><FTPPDFURL>ftp://ftp.legis.state.tx.us/bills/84R/fiscalNotes/PDF/house_bills/HB02800_HB02899/HB02893I.PDF</FTPPDFURL></version></versions></fiscalNote></docTypes></billtext></billhistory>