<billhistory bill="84(R) HB 599" lastUpdate="5/21/2015 2:00:49 AM" source="Texas Legislature Online website (ftp://ftp.legis.state.tx.us) - Texas Legislative Council" disclaimer="The Texas Legislative Council makes no representation as to the completeness, timeliness, or accuracy of this data and makes no warranty in regard to its use." xmlns=""><lastaction>05/20/2015 S Referred to Business &amp; Commerce</lastaction><caption version="Engrossed">Relating to energy savings performance contracts entered into by public institutions of higher education.</caption><authors>Clardy</authors><coauthors /><sponsors /><cosponsors /><subjects><subject>Education--Higher--Finance (I0232)</subject><subject>Education--Higher--Institutions &amp; Programs (I0223)</subject><subject>Energy--Conservation (I0317)</subject><subject>STATE ENERGY CONSERVATION OFFICE (V0110)</subject></subjects><companions /><enablinglegislation /><committees><house name="Higher Education" status="Out of committee" ayeVotes="8" nayVotes="0" presentNotVotingVotes="0" absentVotes="1" subcommitteeName="" subcommitteeStatus="" /><senate name="Business &amp; Commerce" status="In committee" ayeVotes="0" nayVotes="0" presentNotVotingVotes="0" absentVotes="0" subcommitteeName="" subcommitteeStatus="" /></committees><conferees><house /><senate /></conferees><actions><action><actionNumber>H001</actionNumber><date>1/6/2015</date><description>Filed</description><comment /><actionTimestamp /></action><action><actionNumber>H005</actionNumber><date>2/19/2015</date><description>Read first time</description><comment /><actionTimestamp /></action><action><actionNumber>H070</actionNumber><date>2/19/2015</date><description>Referred to Higher Education</description><comment /><actionTimestamp>2/19/2015 11:53:00 AM</actionTimestamp></action><action><actionNumber>H228</actionNumber><date>2/25/2015</date><description>Scheduled for public hearing on . . .</description><comment /><actionTimestamp /></action><action><actionNumber>H215</actionNumber><date>2/25/2015</date><description>Considered in public hearing</description><comment /><actionTimestamp /></action><action><actionNumber>H240</actionNumber><date>2/25/2015</date><description>Testimony taken/registration(s) recorded in committee</description><comment /><actionTimestamp /></action><action><actionNumber>H245</actionNumber><date>2/25/2015</date><description>Left pending in committee</description><comment /><actionTimestamp /></action><action><actionNumber>H215</actionNumber><date>3/11/2015</date><description>Considered in public hearing</description><comment /><actionTimestamp /></action><action><actionNumber>H241</actionNumber><date>3/11/2015</date><description>Committee substitute considered in committee</description><comment /><actionTimestamp /></action><action><actionNumber>H255</actionNumber><date>3/11/2015</date><description>Recommended to be sent to Local &amp; Consent</description><comment /><actionTimestamp /></action><action><actionNumber>H252</actionNumber><date>3/11/2015</date><description>Reported favorably as substituted</description><comment /><actionTimestamp /></action><action><actionNumber>H853</actionNumber><date>3/17/2015</date><description>Comte report filed with Committee Coordinator</description><comment /><actionTimestamp /></action><action><actionNumber>H855</actionNumber><date>3/17/2015</date><description>Committee report distributed</description><comment /><actionTimestamp>3/17/2015 3:11:00 PM</actionTimestamp></action><action><actionNumber>H410</actionNumber><date>3/19/2015</date><description>Comm. report sent to Local &amp; Consent Calendar</description><comment /><actionTimestamp /></action><action><actionNumber>H416</actionNumber><date>4/6/2015</date><description>Considered in Local &amp; Consent Calendars</description><comment /><actionTimestamp /></action><action><actionNumber>H465</actionNumber><date>4/9/2015</date><description>Placed on Local, Consent, and Res. Calendar</description><comment /><actionTimestamp /></action><action><actionNumber>H500</actionNumber><date>4/9/2015</date><description>Withdrawn from calendar</description><comment /><actionTimestamp /></action><action><actionNumber>H677</actionNumber><date>4/9/2015</date><description>Returned to Local &amp; Consent Calendars Comm.</description><comment /><actionTimestamp /></action><action><actionNumber>H416</actionNumber><date>4/9/2015</date><description>Considered in Local &amp; Consent Calendars</description><comment /><actionTimestamp /></action><action><actionNumber>H475</actionNumber><date>4/9/2015</date><description>Transferred to Calendars Committee</description><comment /><actionTimestamp /></action><action><actionNumber>H400</actionNumber><date>4/9/2015</date><description>Committee report sent to Calendars</description><comment /><actionTimestamp /></action><action><actionNumber>H415</actionNumber><date>4/9/2015</date><description>Considered in Calendars</description><comment /><actionTimestamp /></action><action><actionNumber>H435</actionNumber><date>4/13/2015</date><description>Placed on General State Calendar</description><comment /><actionTimestamp /></action><action><actionNumber>H515</actionNumber><date>4/13/2015</date><description>Read 2nd time</description><comment /><actionTimestamp /></action><action><actionNumber>H535</actionNumber><date>4/13/2015</date><description>Passed to engrossment</description><comment /><actionTimestamp /></action><action><actionNumber>H550</actionNumber><date>4/14/2015</date><description>Read 3rd time</description><comment /><actionTimestamp /></action><action><actionNumber>H555</actionNumber><date>4/14/2015</date><description>Passed</description><comment /><actionTimestamp /></action><action><actionNumber>H630</actionNumber><date>4/14/2015</date><description>Record vote</description><comment>RV#215</comment><actionTimestamp /></action><action><actionNumber>H633</actionNumber><date>4/14/2015</date><description>Statement(s) of vote recorded in Journal</description><comment /><actionTimestamp /></action><action><actionNumber>H835</actionNumber><date>4/14/2015</date><description>Reported engrossed</description><comment /><actionTimestamp>4/14/2015 1:57:00 PM</actionTimestamp></action><action><actionNumber>S800</actionNumber><date>4/14/2015</date><description>Received from the House</description><comment /><actionTimestamp /></action><action><actionNumber>S005</actionNumber><date>5/20/2015</date><description>Read first time</description><comment /><actionTimestamp /></action><action><actionNumber>S040</actionNumber><date>5/20/2015</date><description>Referred to Business &amp; Commerce</description><comment /><actionTimestamp /></action></actions><billtext><docTypes><bill><versions><version><versionDescription>Introduced</versionDescription><WebHTMLURL>http://www.legis.state.tx.us/tlodocs/84R/billtext/html/HB00599I.HTM</WebHTMLURL><WebPDFURL>http://www.legis.state.tx.us/tlodocs/84R/billtext/pdf/HB00599I.PDF</WebPDFURL><FTPHTMLURL>ftp://ftp.legis.state.tx.us/bills/84R/billtext/HTML/house_bills/HB00500_HB00599/HB00599I.HTM</FTPHTMLURL><FTPPDFURL>ftp://ftp.legis.state.tx.us/bills/84R/billtext/PDF/house_bills/HB00500_HB00599/HB00599I.PDF</FTPPDFURL></version><version><versionDescription>House Committee Report</versionDescription><WebHTMLURL>http://www.legis.state.tx.us/tlodocs/84R/billtext/html/HB00599H.HTM</WebHTMLURL><WebPDFURL>http://www.legis.state.tx.us/tlodocs/84R/billtext/pdf/HB00599H.PDF</WebPDFURL><FTPHTMLURL>ftp://ftp.legis.state.tx.us/bills/84R/billtext/HTML/house_bills/HB00500_HB00599/HB00599H.HTM</FTPHTMLURL><FTPPDFURL>ftp://ftp.legis.state.tx.us/bills/84R/billtext/PDF/house_bills/HB00500_HB00599/HB00599H.PDF</FTPPDFURL></version><version><versionDescription>Engrossed</versionDescription><WebHTMLURL>http://www.legis.state.tx.us/tlodocs/84R/billtext/html/HB00599E.HTM</WebHTMLURL><WebPDFURL>http://www.legis.state.tx.us/tlodocs/84R/billtext/pdf/HB00599E.PDF</WebPDFURL><FTPHTMLURL>ftp://ftp.legis.state.tx.us/bills/84R/billtext/HTML/house_bills/HB00500_HB00599/HB00599E.HTM</FTPHTMLURL><FTPPDFURL>ftp://ftp.legis.state.tx.us/bills/84R/billtext/PDF/house_bills/HB00500_HB00599/HB00599E.PDF</FTPPDFURL></version></versions></bill><analysis><versions><version><versionDescription>House Committee Report</versionDescription><WebHTMLURL>http://www.legis.state.tx.us/tlodocs/84R/analysis/html/HB00599H.HTM</WebHTMLURL><WebPDFURL>http://www.legis.state.tx.us/tlodocs/84R/analysis/pdf/HB00599H.PDF</WebPDFURL><FTPHTMLURL>ftp://ftp.legis.state.tx.us/bills/84R/analysis/HTML/house_bills/HB00500_HB00599/HB00599H.HTM</FTPHTMLURL><FTPPDFURL>ftp://ftp.legis.state.tx.us/bills/84R/analysis/PDF/house_bills/HB00500_HB00599/HB00599H.PDF</FTPPDFURL></version></versions></analysis><fiscalNote><versions><version><versionDescription>Introduced</versionDescription><WebHTMLURL>http://www.legis.state.tx.us/tlodocs/84R/fiscalNotes/html/HB00599I.HTM</WebHTMLURL><WebPDFURL>http://www.legis.state.tx.us/tlodocs/84R/fiscalNotes/pdf/HB00599I.PDF</WebPDFURL><FTPHTMLURL>ftp://ftp.legis.state.tx.us/bills/84R/fiscalNotes/HTML/house_bills/HB00500_HB00599/HB00599I.HTM</FTPHTMLURL><FTPPDFURL>ftp://ftp.legis.state.tx.us/bills/84R/fiscalNotes/PDF/house_bills/HB00500_HB00599/HB00599I.PDF</FTPPDFURL></version><version><versionDescription>House Committee Report</versionDescription><WebHTMLURL>http://www.legis.state.tx.us/tlodocs/84R/fiscalNotes/html/HB00599H.HTM</WebHTMLURL><WebPDFURL>http://www.legis.state.tx.us/tlodocs/84R/fiscalNotes/pdf/HB00599H.PDF</WebPDFURL><FTPHTMLURL>ftp://ftp.legis.state.tx.us/bills/84R/fiscalNotes/HTML/house_bills/HB00500_HB00599/HB00599H.HTM</FTPHTMLURL><FTPPDFURL>ftp://ftp.legis.state.tx.us/bills/84R/fiscalNotes/PDF/house_bills/HB00500_HB00599/HB00599H.PDF</FTPPDFURL></version><version><versionDescription>Engrossed</versionDescription><WebHTMLURL>http://www.legis.state.tx.us/tlodocs/84R/fiscalNotes/html/HB00599E.HTM</WebHTMLURL><WebPDFURL>http://www.legis.state.tx.us/tlodocs/84R/fiscalNotes/pdf/HB00599E.PDF</WebPDFURL><FTPHTMLURL>ftp://ftp.legis.state.tx.us/bills/84R/fiscalNotes/HTML/house_bills/HB00500_HB00599/HB00599E.HTM</FTPHTMLURL><FTPPDFURL>ftp://ftp.legis.state.tx.us/bills/84R/fiscalNotes/PDF/house_bills/HB00500_HB00599/HB00599E.PDF</FTPPDFURL></version></versions></fiscalNote></docTypes></billtext></billhistory>