<billhistory bill="85(R) HB 1011" lastUpdate="3/7/2017 2:00:10 AM" source="Texas Legislature Online website (ftp://ftp.legis.state.tx.us) - Texas Legislative Council" disclaimer="The Texas Legislative Council makes no representation as to the completeness, timeliness, or accuracy of this data and makes no warranty in regard to its use." xmlns=""><lastaction>03/06/2017 H Referred to Criminal Jurisprudence: Mar  6 2017  3:34PM </lastaction><caption version="Introduced">Relating to the procedure for an application for a writ of habeas corpus after a plea of guilty or nolo contendere.</caption><authors>Alonzo</authors><coauthors /><sponsors /><cosponsors /><subjects><subject>Criminal Procedure--General (I0208)</subject><subject>HABEAS CORPUS (S0263)</subject></subjects><companions /><enablinglegislation /><committees><house name="Criminal Jurisprudence" status="In committee" ayeVotes="0" nayVotes="0" presentNotVotingVotes="0" absentVotes="0" subcommitteeName="" subcommitteeStatus="" /><senate name="" status="" ayeVotes="0" nayVotes="0" presentNotVotingVotes="0" absentVotes="0" subcommitteeName="" subcommitteeStatus="" /></committees><conferees><house /><senate /></conferees><actions><action><actionNumber>H001</actionNumber><date>1/12/2017</date><description>Filed</description><comment /><actionTimestamp /></action><action><actionNumber>H005</actionNumber><date>3/6/2017</date><description>Read first time</description><comment /><actionTimestamp /></action><action><actionNumber>H035</actionNumber><date>3/6/2017</date><description>Referred to Criminal Jurisprudence</description><comment /><actionTimestamp>3/6/2017 3:34:00 PM</actionTimestamp></action></actions><billtext><docTypes><bill><versions><version><versionDescription>Introduced</versionDescription><WebHTMLURL>http://www.legis.state.tx.us/tlodocs/85R/billtext/html/HB01011I.HTM</WebHTMLURL><WebPDFURL>http://www.legis.state.tx.us/tlodocs/85R/billtext/pdf/HB01011I.PDF</WebPDFURL><FTPHTMLURL>ftp://ftp.legis.state.tx.us/bills/85R/billtext/HTML/house_bills/HB01000_HB01099/HB01011I.HTM</FTPHTMLURL><FTPPDFURL>ftp://ftp.legis.state.tx.us/bills/85R/billtext/PDF/house_bills/HB01000_HB01099/HB01011I.PDF</FTPPDFURL></version></versions></bill><analysis><versions /></analysis><fiscalNote><versions /></fiscalNote></docTypes></billtext></billhistory>