<billhistory bill="85(R) HB 1028" lastUpdate="3/7/2017 2:00:10 AM" source="Texas Legislature Online website (ftp://ftp.legis.state.tx.us) - Texas Legislative Council" disclaimer="The Texas Legislative Council makes no representation as to the completeness, timeliness, or accuracy of this data and makes no warranty in regard to its use." xmlns=""><lastaction>03/06/2017 H Referred to Transportation: Mar  6 2017  3:34PM </lastaction><caption version="Introduced">Relating to the designation of Farm-to-Market Road 2666 in San Jacinto County as the Josey Scott Memorial Highway.</caption><authors>Bailes</authors><coauthors /><sponsors /><cosponsors /><subjects><subject>SAN JACINTO COUNTY (G0543)</subject><subject>Highways (I0390)</subject><subject>JOSEY SCOTT MEMORIAL HIGHWAY (S0835)</subject></subjects><companions /><enablinglegislation /><committees><house name="Transportation" status="In committee" ayeVotes="0" nayVotes="0" presentNotVotingVotes="0" absentVotes="0" subcommitteeName="" subcommitteeStatus="" /><senate name="" status="" ayeVotes="0" nayVotes="0" presentNotVotingVotes="0" absentVotes="0" subcommitteeName="" subcommitteeStatus="" /></committees><conferees><house /><senate /></conferees><actions><action><actionNumber>H001</actionNumber><date>1/13/2017</date><description>Filed</description><comment /><actionTimestamp /></action><action><actionNumber>H005</actionNumber><date>3/6/2017</date><description>Read first time</description><comment /><actionTimestamp /></action><action><actionNumber>H160</actionNumber><date>3/6/2017</date><description>Referred to Transportation</description><comment /><actionTimestamp>3/6/2017 3:34:00 PM</actionTimestamp></action></actions><billtext><docTypes><bill><versions><version><versionDescription>Introduced</versionDescription><WebHTMLURL>http://www.legis.state.tx.us/tlodocs/85R/billtext/html/HB01028I.HTM</WebHTMLURL><WebPDFURL>http://www.legis.state.tx.us/tlodocs/85R/billtext/pdf/HB01028I.PDF</WebPDFURL><FTPHTMLURL>ftp://ftp.legis.state.tx.us/bills/85R/billtext/HTML/house_bills/HB01000_HB01099/HB01028I.HTM</FTPHTMLURL><FTPPDFURL>ftp://ftp.legis.state.tx.us/bills/85R/billtext/PDF/house_bills/HB01000_HB01099/HB01028I.PDF</FTPPDFURL></version></versions></bill><analysis><versions /></analysis><fiscalNote><versions /></fiscalNote></docTypes></billtext></billhistory>