<billhistory bill="84(R) HB 1145" lastUpdate="4/28/2015 2:00:08 AM" source="Texas Legislature Online website (ftp://ftp.legis.state.tx.us) - Texas Legislative Council" disclaimer="The Texas Legislative Council makes no representation as to the completeness, timeliness, or accuracy of this data and makes no warranty in regard to its use." xmlns=""><lastaction>04/27/2015 H Failed to receive affirmative vote in comm.</lastaction><caption version="Introduced">Relating to the establishment of an information clearinghouse to facilitate embryo adoption and the provision by physicians of embryo adoption information to certain patients.</caption><authors>Raney | Zerwas</authors><coauthors /><sponsors /><cosponsors /><subjects><subject>Health Care Providers (I0387)</subject><subject>Health--General (I0385)</subject><subject>ADOPTION (S0101)</subject><subject>PHYSICIANS (S1282)</subject><subject>HEALTH &amp; HUMAN SERVICES COMMISSION (V0177)</subject><subject>STATE HEALTH SERVICES, DEPARTMENT OF (V0463)</subject></subjects><companions /><enablinglegislation /><committees><house name="Public Health" status="In committee" ayeVotes="0" nayVotes="0" presentNotVotingVotes="0" absentVotes="0" subcommitteeName="" subcommitteeStatus="" /><senate name="" status="" ayeVotes="0" nayVotes="0" presentNotVotingVotes="0" absentVotes="0" subcommitteeName="" subcommitteeStatus="" /></committees><conferees><house /><senate /></conferees><actions><action><actionNumber>H001</actionNumber><date>2/4/2015</date><description>Filed</description><comment /><actionTimestamp /></action><action><actionNumber>H005</actionNumber><date>3/3/2015</date><description>Read first time</description><comment /><actionTimestamp /></action><action><actionNumber>H120</actionNumber><date>3/3/2015</date><description>Referred to Public Health</description><comment /><actionTimestamp>3/3/2015 1:59:00 PM</actionTimestamp></action><action><actionNumber>H228</actionNumber><date>4/14/2015</date><description>Scheduled for public hearing on . . .</description><comment /><actionTimestamp /></action><action><actionNumber>H215</actionNumber><date>4/14/2015</date><description>Considered in public hearing</description><comment /><actionTimestamp /></action><action><actionNumber>H241</actionNumber><date>4/14/2015</date><description>Committee substitute considered in committee</description><comment /><actionTimestamp /></action><action><actionNumber>H240</actionNumber><date>4/14/2015</date><description>Testimony taken/registration(s) recorded in committee</description><comment /><actionTimestamp /></action><action><actionNumber>H245</actionNumber><date>4/14/2015</date><description>Left pending in committee</description><comment /><actionTimestamp /></action><action><actionNumber>H216</actionNumber><date>4/27/2015</date><description>Considered in formal meeting</description><comment /><actionTimestamp /></action><action><actionNumber>H241</actionNumber><date>4/27/2015</date><description>Committee substitute considered in committee</description><comment /><actionTimestamp /></action><action><actionNumber>H249</actionNumber><date>4/27/2015</date><description>Failed to receive affirmative vote in comm.</description><comment /><actionTimestamp /></action></actions><billtext><docTypes><bill><versions><version><versionDescription>Introduced</versionDescription><WebHTMLURL>http://www.legis.state.tx.us/tlodocs/84R/billtext/html/HB01145I.HTM</WebHTMLURL><WebPDFURL>http://www.legis.state.tx.us/tlodocs/84R/billtext/pdf/HB01145I.PDF</WebPDFURL><FTPHTMLURL>ftp://ftp.legis.state.tx.us/bills/84R/billtext/HTML/house_bills/HB01100_HB01199/HB01145I.HTM</FTPHTMLURL><FTPPDFURL>ftp://ftp.legis.state.tx.us/bills/84R/billtext/PDF/house_bills/HB01100_HB01199/HB01145I.PDF</FTPPDFURL></version></versions></bill><analysis><versions /></analysis><fiscalNote><versions><version><versionDescription>Introduced</versionDescription><WebHTMLURL>http://www.legis.state.tx.us/tlodocs/84R/fiscalNotes/html/HB01145I.HTM</WebHTMLURL><WebPDFURL>http://www.legis.state.tx.us/tlodocs/84R/fiscalNotes/pdf/HB01145I.PDF</WebPDFURL><FTPHTMLURL>ftp://ftp.legis.state.tx.us/bills/84R/fiscalNotes/HTML/house_bills/HB01100_HB01199/HB01145I.HTM</FTPHTMLURL><FTPPDFURL>ftp://ftp.legis.state.tx.us/bills/84R/fiscalNotes/PDF/house_bills/HB01100_HB01199/HB01145I.PDF</FTPPDFURL></version></versions></fiscalNote></docTypes></billtext></billhistory>