<billhistory bill="85(R) SB 1183" lastUpdate="3/10/2017 2:01:04 AM" source="Texas Legislature Online website (ftp://ftp.legis.state.tx.us) - Texas Legislative Council" disclaimer="The Texas Legislative Council makes no representation as to the completeness, timeliness, or accuracy of this data and makes no warranty in regard to its use." xmlns=""><lastaction>03/09/2017 S Referred to Criminal Justice</lastaction><caption version="Introduced">Relating to procedures regarding criminal defendants who are or may be persons with a mental illness or an intellectual disability and to the period for which a person may be committed to receive certain temporary mental health services.</caption><authors>Perry</authors><coauthors /><sponsors /><cosponsors /><subjects><subject>Corrections--Jails &amp; Prisons (I0092)</subject><subject>Crimes--Miscellaneous (I0200)</subject><subject>Criminal Procedure--Bail &amp; Pretrial Release (I0202)</subject><subject>Criminal Procedure--Pretrial Procedure (I0203)</subject><subject>Mental Health &amp; Substance Abuse (I0019)</subject><subject>MENTAL INCOMPETENCY (S0019)</subject><subject>PSYCHOLOGISTS (S2025)</subject><subject>HEALTH &amp; HUMAN SERVICES COMMISSION (V0177)</subject></subjects><companions /><enablinglegislation /><committees><house name="" status="" ayeVotes="0" nayVotes="0" presentNotVotingVotes="0" absentVotes="0" subcommitteeName="" subcommitteeStatus="" /><senate name="Criminal Justice" status="In committee" ayeVotes="0" nayVotes="0" presentNotVotingVotes="0" absentVotes="0" subcommitteeName="" subcommitteeStatus="" /></committees><conferees><house /><senate /></conferees><actions><action><actionNumber>S000</actionNumber><date>3/1/2017</date><description>Received by the Secretary of the Senate</description><comment /><actionTimestamp /></action><action><actionNumber>S001</actionNumber><date>3/1/2017</date><description>Filed</description><comment /><actionTimestamp /></action><action><actionNumber>S005</actionNumber><date>3/9/2017</date><description>Read first time</description><comment /><actionTimestamp /></action><action><actionNumber>S030</actionNumber><date>3/9/2017</date><description>Referred to Criminal Justice</description><comment /><actionTimestamp /></action></actions><billtext><docTypes><bill><versions><version><versionDescription>Introduced</versionDescription><WebHTMLURL>http://www.legis.state.tx.us/tlodocs/85R/billtext/html/SB01183I.HTM</WebHTMLURL><WebPDFURL>http://www.legis.state.tx.us/tlodocs/85R/billtext/pdf/SB01183I.PDF</WebPDFURL><FTPHTMLURL>ftp://ftp.legis.state.tx.us/bills/85R/billtext/HTML/senate_bills/SB01100_SB01199/SB01183I.HTM</FTPHTMLURL><FTPPDFURL>ftp://ftp.legis.state.tx.us/bills/85R/billtext/PDF/senate_bills/SB01100_SB01199/SB01183I.PDF</FTPPDFURL></version></versions></bill><analysis><versions /></analysis><fiscalNote><versions /></fiscalNote></docTypes></billtext></billhistory>