<billhistory bill="84(R) SB 1162" lastUpdate="6/19/2015 2:00:37 AM" source="Texas Legislature Online website (ftp://ftp.legis.state.tx.us) - Texas Legislative Council" disclaimer="The Texas Legislative Council makes no representation as to the completeness, timeliness, or accuracy of this data and makes no warranty in regard to its use." xmlns=""><lastaction>06/17/2015 E Effective on . . . . . . . . . . . . . . .</lastaction><caption version="Enrolled">Relating to the nonsubstantive revision of certain local laws concerning water and wastewater special districts, including conforming amendments.</caption><authors>Hancock</authors><coauthors /><sponsors>Keffer</sponsors><cosponsors /><subjects><subject>CAMERON COUNTY DRAINAGE DISTRICT NO. 1 (D1251)</subject><subject>CAMERON COUNTY DRAINAGE DISTRICT NO. 3 (D1285)</subject><subject>CHOCTAW WATERSHED WATER IMPROVEMENT DISTRICT (D1268)</subject><subject>DONAHOE CREEK WATERSHED AUTHORITY (D1267)</subject><subject>DUVAL COUNTY CONSERVATION &amp; RECLAMATION DISTRICT (D0125)</subject><subject>FALLBROOK UTILITY DISTRICT (D1269)</subject><subject>FLAMINGO ISLES MUNICIPAL UTILITY DISTRICT OF GALVESTON COUNTY, TEXAS (D1272)</subject><subject>HARRIS COUNTY WATER CONTROL &amp; IMPROVEMENT DISTRICT - FONDREN ROAD (D1270)</subject><subject>HULL FRESH WATER SUPPLY DISTRICT (D1253)</subject><subject>INVERNESS FOREST IMPROVEMENT DISTRICT (D1271)</subject><subject>JEFFERSON COUNTY WATER CONTROL &amp; IMPROVEMENT DIST. NO. 10 (D0120)</subject><subject>JOHNSON COUNTY SPECIAL UTILITY DISTRICT (D0367)</subject><subject>LAZY RIVER IMPROVEMENT DISTRICT (D1273)</subject><subject>MEDINA COUNTY WATER CONTROL &amp; IMPROVEMENT DISTRICT NO. 2 (D1276)</subject><subject>MEMORIAL VILLAGES WATER AUTHORITY (D1254)</subject><subject>MUENSTER WATER DISTRICT (D1282)</subject><subject>OLD RIVER DRAINAGE DISTRICT OF LIBERTY COUNTY NO. 1 (D1252)</subject><subject>PETTUS MUNICIPAL UTILITY DISTRICT (D1255)</subject><subject>PORT MANSFIELD PUBLIC UTILITY DISTRICT (D1256)</subject><subject>PORT O'CONNOR IMPROVEMENT DISTRICT (D1262)</subject><subject>RIO GRANDE PALMS WATER DISTRICT (D1277)</subject><subject>SAGEMEADOW UTILITY DISTRICT (D1258)</subject><subject>SAN LEON MUNICIPAL UTILITY DISTRICT OF GALVESTON COUNTY, TEXAS (D1278)</subject><subject>SAN PATRICIO COUNTY DRAINAGE DISTRICT (D1249)</subject><subject>SHASLA PUBLIC UTILITY DISTRICT (D1286)</subject><subject>SOUTH TEXAS WATER AUTHORITY (D1283)</subject><subject>SPANISH COVE PUBLIC UTILITY DISTRICT (D1259)</subject><subject>SPENCER ROAD PUBLIC UTILITY DISTRICT (D1260)</subject><subject>SPRING MEADOWS MUNICIPAL UTILITIES DISTRICT (D0008)</subject><subject>TATTOR ROAD MUNICIPAL DISTRICT (D1279)</subject><subject>THUNDERBIRD UTILITY DISTRICT (D1261)</subject><subject>TREASURE ISLAND MUNICIPAL UTILITY DISTRICT OF BRAZORIA COUNTY, TEXAS (D1280)</subject><subject>UPPER COLORADO RIVER AUTHORITY (D0250)</subject><subject>UPPER JASPER COUNTY WATER AUTHORITY (D1281)</subject><subject>VARNER CREEK UTILITY DISTRICT (D1263)</subject><subject>WEST CEDAR CREEK MUNICIPAL UTILITY DISTRICT (D1264)</subject><subject>WEST JEFFERSON COUNTY MUNICIPAL WATER DISTRICT (D1284)</subject><subject>WEST TRAVIS COUNTY MUNICIPAL UTILITY DISTRICT NO. 3 (D1265)</subject><subject>WEST TRAVIS COUNTY MUNICIPAL UTILITY DISTRICT NO. 5 (D1029)</subject><subject>WILLACY COUNTY DRAINAGE DISTRICT NO. 2 (D1250)</subject><subject>WILLIAMSON COUNTY MUNICIPAL UTILITY DISTRICT NO. 12 (D0355)</subject><subject>WILLIAMSON COUNTY MUNICIPAL UTILITY DISTRICT NO. 13 (D0354)</subject><subject>WILLIAMSON COUNTY WATER, SEWER, IRRIGATION, AND DRAINAGE DISTRICT NO. 3 (D1266)</subject><subject>WILLOW CREEK WATER CONTROL DISTRICT (D1275)</subject><subject>WISE COUNTY WATER SUPPLY DISTRICT (D1274)</subject><subject>WOOD TRACT MUNICIPAL UTILITY DISTRICT NO. 1, OF MONTGOMERY COUNTY, TEXAS (D1257)</subject><subject>Special Districts &amp; Authorities--Groundwater Conserve Dist. (I0013)</subject><subject>Special Districts &amp; Authorities--Miscellaneous (I0770)</subject><subject>Special Districts &amp; Authorities--Municipal Utility Districts (I0009)</subject><subject>Special Districts &amp; Authorities--River Authorities (I0011)</subject><subject>Special Districts &amp; Authorities--Water &amp; Utility (I0755)</subject><subject>Special Districts &amp; Authorities--Water Control Improve Dist. (I0012)</subject><subject>Statutory Revision (I0771)</subject></subjects><companions /><enablinglegislation /><committees><house name="Natural Resources" status="Out of committee" ayeVotes="10" nayVotes="0" presentNotVotingVotes="0" absentVotes="1" subcommitteeName="" subcommitteeStatus="" /><senate name="Intergovernmental Relations" status="Out of committee" ayeVotes="5" nayVotes="0" presentNotVotingVotes="0" absentVotes="2" subcommitteeName="" subcommitteeStatus="" /></committees><conferees><house /><senate /></conferees><actions><action><actionNumber>S000</actionNumber><date>3/10/2015</date><description>Received by the Secretary of the Senate</description><comment /><actionTimestamp /></action><action><actionNumber>S001</actionNumber><date>3/10/2015</date><description>Filed</description><comment /><actionTimestamp /></action><action><actionNumber>S005</actionNumber><date>3/17/2015</date><description>Read first time</description><comment /><actionTimestamp /></action><action><actionNumber>S080</actionNumber><date>3/17/2015</date><description>Referred to Intergovernmental Relations</description><comment /><actionTimestamp /></action><action><actionNumber>S228</actionNumber><date>4/13/2015</date><description>Scheduled for public hearing on  . . .</description><comment /><actionTimestamp /></action><action><actionNumber>S260</actionNumber><date>4/13/2015</date><description>Considered in public hearing</description><comment /><actionTimestamp /></action><action><actionNumber>S275</actionNumber><date>4/13/2015</date><description>Left pending in committee</description><comment /><actionTimestamp /></action><action><actionNumber>S260</actionNumber><date>4/15/2015</date><description>Considered in public hearing</description><comment /><actionTimestamp /></action><action><actionNumber>S285</actionNumber><date>4/22/2015</date><description>Reported favorably w/o amendments</description><comment /><actionTimestamp /></action><action><actionNumber>S405</actionNumber><date>4/22/2015</date><description>Recommended for local &amp; uncontested calendar</description><comment /><actionTimestamp /></action><action><actionNumber>S855</actionNumber><date>4/22/2015</date><description>Committee report printed and distributed</description><comment /><actionTimestamp>4/22/2015 11:20:00 AM</actionTimestamp></action><action><actionNumber>S400</actionNumber><date>4/23/2015</date><description>Placed on intent calendar</description><comment /><actionTimestamp /></action><action><actionNumber>S401</actionNumber><date>4/28/2015</date><description>Not again placed on intent calendar</description><comment /><actionTimestamp /></action><action><actionNumber>S430</actionNumber><date>4/30/2015</date><description>Placed on local &amp; uncontested calendar</description><comment /><actionTimestamp /></action><action><actionNumber>S520</actionNumber><date>4/30/2015</date><description>Laid before the Senate</description><comment /><actionTimestamp /></action><action><actionNumber>S522</actionNumber><date>4/30/2015</date><description>Read 2nd time &amp; passed to engrossment</description><comment /><actionTimestamp /></action><action><actionNumber>S626</actionNumber><date>4/30/2015</date><description>Vote recorded in Journal</description><comment /><actionTimestamp /></action><action><actionNumber>S572</actionNumber><date>4/30/2015</date><description>Three day rule suspended</description><comment /><actionTimestamp /></action><action><actionNumber>S625</actionNumber><date>4/30/2015</date><description>Record vote</description><comment /><actionTimestamp /></action><action><actionNumber>S575</actionNumber><date>4/30/2015</date><description>Read 3rd time</description><comment /><actionTimestamp /></action><action><actionNumber>S576</actionNumber><date>4/30/2015</date><description>Passed</description><comment /><actionTimestamp /></action><action><actionNumber>S625</actionNumber><date>4/30/2015</date><description>Record vote</description><comment /><actionTimestamp /></action><action><actionNumber>S835</actionNumber><date>4/30/2015</date><description>Reported engrossed</description><comment /><actionTimestamp /></action><action><actionNumber>H800</actionNumber><date>4/30/2015</date><description>Received from the Senate</description><comment /><actionTimestamp /></action><action><actionNumber>H005</actionNumber><date>5/4/2015</date><description>Read first time</description><comment /><actionTimestamp /></action><action><actionNumber>H110</actionNumber><date>5/4/2015</date><description>Referred to Natural Resources</description><comment /><actionTimestamp>5/4/2015 7:19:00 PM</actionTimestamp></action><action><actionNumber>H654</actionNumber><date>5/15/2015</date><description>Posting rule suspended</description><comment /><actionTimestamp /></action><action><actionNumber>H228</actionNumber><date>5/18/2015</date><description>Scheduled for public hearing on . . .</description><comment /><actionTimestamp /></action><action><actionNumber>H215</actionNumber><date>5/18/2015</date><description>Considered in public hearing</description><comment /><actionTimestamp /></action><action><actionNumber>H240</actionNumber><date>5/18/2015</date><description>Testimony taken/registration(s) recorded in committee</description><comment /><actionTimestamp /></action><action><actionNumber>H245</actionNumber><date>5/18/2015</date><description>Left pending in committee</description><comment /><actionTimestamp /></action><action><actionNumber>H216</actionNumber><date>5/21/2015</date><description>Considered in formal meeting</description><comment /><actionTimestamp /></action><action><actionNumber>H255</actionNumber><date>5/21/2015</date><description>Recommended to be sent to Local &amp; Consent</description><comment /><actionTimestamp /></action><action><actionNumber>H250</actionNumber><date>5/21/2015</date><description>Reported favorably w/o amendment(s)</description><comment /><actionTimestamp /></action><action><actionNumber>H853</actionNumber><date>5/21/2015</date><description>Comte report filed with Committee Coordinator</description><comment /><actionTimestamp /></action><action><actionNumber>H855</actionNumber><date>5/21/2015</date><description>Committee report distributed</description><comment /><actionTimestamp>5/21/2015 7:24:00 PM</actionTimestamp></action><action><actionNumber>H410</actionNumber><date>5/22/2015</date><description>Comm. report sent to Local &amp; Consent Calendar</description><comment /><actionTimestamp /></action><action><actionNumber>H416</actionNumber><date>5/26/2015</date><description>Considered in Local &amp; Consent Calendars</description><comment /><actionTimestamp /></action><action><actionNumber>H465</actionNumber><date>5/27/2015</date><description>Placed on Local, Consent, and Res. Calendar</description><comment /><actionTimestamp /></action><action><actionNumber>H515</actionNumber><date>5/27/2015</date><description>Read 2nd time</description><comment /><actionTimestamp /></action><action><actionNumber>H540</actionNumber><date>5/27/2015</date><description>Passed to 3rd reading</description><comment /><actionTimestamp /></action><action><actionNumber>H550</actionNumber><date>5/27/2015</date><description>Read 3rd time</description><comment /><actionTimestamp /></action><action><actionNumber>H555</actionNumber><date>5/27/2015</date><description>Passed</description><comment /><actionTimestamp /></action><action><actionNumber>H630</actionNumber><date>5/27/2015</date><description>Record vote</description><comment>RV#1556</comment><actionTimestamp /></action><action><actionNumber>S805</actionNumber><date>5/28/2015</date><description>House passage reported</description><comment /><actionTimestamp /></action><action><actionNumber>S840</actionNumber><date>5/28/2015</date><description>Reported enrolled</description><comment /><actionTimestamp /></action><action><actionNumber>S850</actionNumber><date>5/30/2015</date><description>Signed in the Senate</description><comment /><actionTimestamp /></action><action><actionNumber>H850</actionNumber><date>5/30/2015</date><description>Signed in the House</description><comment /><actionTimestamp /></action><action><actionNumber>E015</actionNumber><date>5/30/2015</date><description>Sent to the Governor</description><comment /><actionTimestamp /></action><action><actionNumber>E020</actionNumber><date>6/17/2015</date><description>Signed by the Governor</description><comment /><actionTimestamp /></action><action><actionNumber>E200</actionNumber><date>6/17/2015</date><description>Effective on . . . . . . . . . . . . . . .</description><comment>April 1, 2017</comment><actionTimestamp /></action></actions><billtext><docTypes><bill><versions><version><versionDescription>Introduced</versionDescription><WebHTMLURL>http://www.legis.state.tx.us/tlodocs/84R/billtext/html/SB01162I.HTM</WebHTMLURL><WebPDFURL>http://www.legis.state.tx.us/tlodocs/84R/billtext/pdf/SB01162I.PDF</WebPDFURL><FTPHTMLURL>ftp://ftp.legis.state.tx.us/bills/84R/billtext/HTML/senate_bills/SB01100_SB01199/SB01162I.HTM</FTPHTMLURL><FTPPDFURL>ftp://ftp.legis.state.tx.us/bills/84R/billtext/PDF/senate_bills/SB01100_SB01199/SB01162I.PDF</FTPPDFURL></version><version><versionDescription>Senate Committee Report</versionDescription><WebHTMLURL>http://www.legis.state.tx.us/tlodocs/84R/billtext/html/SB01162S.HTM</WebHTMLURL><WebPDFURL>http://www.legis.state.tx.us/tlodocs/84R/billtext/pdf/SB01162S.PDF</WebPDFURL><FTPHTMLURL>ftp://ftp.legis.state.tx.us/bills/84R/billtext/HTML/senate_bills/SB01100_SB01199/SB01162S.HTM</FTPHTMLURL><FTPPDFURL>ftp://ftp.legis.state.tx.us/bills/84R/billtext/PDF/senate_bills/SB01100_SB01199/SB01162S.PDF</FTPPDFURL></version><version><versionDescription>Engrossed</versionDescription><WebHTMLURL>http://www.legis.state.tx.us/tlodocs/84R/billtext/html/SB01162E.HTM</WebHTMLURL><WebPDFURL>http://www.legis.state.tx.us/tlodocs/84R/billtext/pdf/SB01162E.PDF</WebPDFURL><FTPHTMLURL>ftp://ftp.legis.state.tx.us/bills/84R/billtext/HTML/senate_bills/SB01100_SB01199/SB01162E.HTM</FTPHTMLURL><FTPPDFURL>ftp://ftp.legis.state.tx.us/bills/84R/billtext/PDF/senate_bills/SB01100_SB01199/SB01162E.PDF</FTPPDFURL></version><version><versionDescription>House Committee Report</versionDescription><WebHTMLURL>http://www.legis.state.tx.us/tlodocs/84R/billtext/html/SB01162H.HTM</WebHTMLURL><WebPDFURL>http://www.legis.state.tx.us/tlodocs/84R/billtext/pdf/SB01162H.PDF</WebPDFURL><FTPHTMLURL>ftp://ftp.legis.state.tx.us/bills/84R/billtext/HTML/senate_bills/SB01100_SB01199/SB01162H.HTM</FTPHTMLURL><FTPPDFURL>ftp://ftp.legis.state.tx.us/bills/84R/billtext/PDF/senate_bills/SB01100_SB01199/SB01162H.PDF</FTPPDFURL></version><version><versionDescription>Enrolled</versionDescription><WebHTMLURL>http://www.legis.state.tx.us/tlodocs/84R/billtext/html/SB01162F.HTM</WebHTMLURL><WebPDFURL>http://www.legis.state.tx.us/tlodocs/84R/billtext/pdf/SB01162F.PDF</WebPDFURL><FTPHTMLURL>ftp://ftp.legis.state.tx.us/bills/84R/billtext/HTML/senate_bills/SB01100_SB01199/SB01162F.HTM</FTPHTMLURL><FTPPDFURL>ftp://ftp.legis.state.tx.us/bills/84R/billtext/PDF/senate_bills/SB01100_SB01199/SB01162F.PDF</FTPPDFURL></version></versions></bill><analysis><versions><version><versionDescription>Introduced</versionDescription><WebHTMLURL>http://www.legis.state.tx.us/tlodocs/84R/analysis/html/SB01162I.HTM</WebHTMLURL><WebPDFURL>http://www.legis.state.tx.us/tlodocs/84R/analysis/pdf/SB01162I.PDF</WebPDFURL><FTPHTMLURL>ftp://ftp.legis.state.tx.us/bills/84R/analysis/HTML/senate_bills/SB01100_SB01199/SB01162I.HTM</FTPHTMLURL><FTPPDFURL>ftp://ftp.legis.state.tx.us/bills/84R/analysis/PDF/senate_bills/SB01100_SB01199/SB01162I.PDF</FTPPDFURL></version><version><versionDescription>House Committee Report</versionDescription><WebHTMLURL>http://www.legis.state.tx.us/tlodocs/84R/analysis/html/SB01162H.HTM</WebHTMLURL><WebPDFURL>http://www.legis.state.tx.us/tlodocs/84R/analysis/pdf/SB01162H.PDF</WebPDFURL><FTPHTMLURL>ftp://ftp.legis.state.tx.us/bills/84R/analysis/HTML/senate_bills/SB01100_SB01199/SB01162H.HTM</FTPHTMLURL><FTPPDFURL>ftp://ftp.legis.state.tx.us/bills/84R/analysis/PDF/senate_bills/SB01100_SB01199/SB01162H.PDF</FTPPDFURL></version></versions></analysis><fiscalNote><versions><version><versionDescription>Introduced</versionDescription><WebHTMLURL>http://www.legis.state.tx.us/tlodocs/84R/fiscalNotes/html/SB01162I.HTM</WebHTMLURL><WebPDFURL>http://www.legis.state.tx.us/tlodocs/84R/fiscalNotes/pdf/SB01162I.PDF</WebPDFURL><FTPHTMLURL>ftp://ftp.legis.state.tx.us/bills/84R/fiscalNotes/HTML/senate_bills/SB01100_SB01199/SB01162I.HTM</FTPHTMLURL><FTPPDFURL>ftp://ftp.legis.state.tx.us/bills/84R/fiscalNotes/PDF/senate_bills/SB01100_SB01199/SB01162I.PDF</FTPPDFURL></version><version><versionDescription>Engrossed</versionDescription><WebHTMLURL>http://www.legis.state.tx.us/tlodocs/84R/fiscalNotes/html/SB01162E.HTM</WebHTMLURL><WebPDFURL>http://www.legis.state.tx.us/tlodocs/84R/fiscalNotes/pdf/SB01162E.PDF</WebPDFURL><FTPHTMLURL>ftp://ftp.legis.state.tx.us/bills/84R/fiscalNotes/HTML/senate_bills/SB01100_SB01199/SB01162E.HTM</FTPHTMLURL><FTPPDFURL>ftp://ftp.legis.state.tx.us/bills/84R/fiscalNotes/PDF/senate_bills/SB01100_SB01199/SB01162E.PDF</FTPPDFURL></version></versions></fiscalNote></docTypes></billtext></billhistory>