<billhistory bill="84(R) SB 10" lastUpdate="5/28/2015 2:01:09 AM" source="Texas Legislature Online website (ftp://ftp.legis.state.tx.us) - Texas Legislative Council" disclaimer="The Texas Legislative Council makes no representation as to the completeness, timeliness, or accuracy of this data and makes no warranty in regard to its use." xmlns=""><lastaction>05/27/2015 H Point of order sustained</lastaction><caption version="House Committee Report">Relating to the prosecution of offenses against public administration, including ethics offenses.</caption><authors>Huffman</authors><coauthors>Birdwell | Campbell | Nichols</coauthors><sponsors>King, Phil</sponsors><cosponsors /><subjects><subject>Courts--Prosecuting Attorneys (I0165)</subject><subject>Ethics (I0345)</subject><subject>Insurance--General (I0445)</subject><subject>State Agencies, Boards &amp; Commissions (I0749)</subject><subject>State Employees (I0626)</subject><subject>State Officers (I0761)</subject><subject>Taxation--Motor Fuels (I0809)</subject><subject>FRAUD (S0166)</subject><subject>RANGERS (S0322)</subject><subject>ATTORNEY GENERAL (V2811)</subject></subjects><companions>HB 1690 by King, Phil, Similar </companions><enablinglegislation /><committees><house name="General Investigating &amp; Ethics" status="Out of committee" ayeVotes="4" nayVotes="3" presentNotVotingVotes="0" absentVotes="0" subcommitteeName="" subcommitteeStatus="" /><senate name="State Affairs" status="Out of committee" ayeVotes="7" nayVotes="2" presentNotVotingVotes="0" absentVotes="0" subcommitteeName="" subcommitteeStatus="" /></committees><conferees><house /><senate /></conferees><actions><action><actionNumber>S000</actionNumber><date>3/4/2015</date><description>Received by the Secretary of the Senate</description><comment /><actionTimestamp /></action><action><actionNumber>S001</actionNumber><date>3/4/2015</date><description>Filed</description><comment /><actionTimestamp /></action><action><actionNumber>S005</actionNumber><date>3/4/2015</date><description>Read first time</description><comment /><actionTimestamp /></action><action><actionNumber>S120</actionNumber><date>3/4/2015</date><description>Referred to State Affairs</description><comment /><actionTimestamp /></action><action><actionNumber>S228</actionNumber><date>3/16/2015</date><description>Scheduled for public hearing on  . . .</description><comment /><actionTimestamp /></action><action><actionNumber>S260</actionNumber><date>3/16/2015</date><description>Considered in public hearing</description><comment /><actionTimestamp /></action><action><actionNumber>S270</actionNumber><date>3/16/2015</date><description>Testimony taken in committee</description><comment /><actionTimestamp /></action><action><actionNumber>S287</actionNumber><date>3/18/2015</date><description>Reported favorably as substituted</description><comment /><actionTimestamp /></action><action><actionNumber>S855</actionNumber><date>3/18/2015</date><description>Committee report printed and distributed</description><comment /><actionTimestamp>3/18/2015 1:24:00 PM</actionTimestamp></action><action><actionNumber>S830</actionNumber><date>3/19/2015</date><description>Co-author authorized</description><comment /><actionTimestamp /></action><action><actionNumber>S400</actionNumber><date>3/23/2015</date><description>Placed on intent calendar</description><comment /><actionTimestamp /></action><action><actionNumber>S830</actionNumber><date>4/8/2015</date><description>Co-author authorized</description><comment /><actionTimestamp /></action><action><actionNumber>S507</actionNumber><date>4/8/2015</date><description>Rules suspended-Regular order of business</description><comment /><actionTimestamp /></action><action><actionNumber>S625</actionNumber><date>4/8/2015</date><description>Record vote</description><comment /><actionTimestamp /></action><action><actionNumber>S521</actionNumber><date>4/8/2015</date><description>Read 2nd time</description><comment /><actionTimestamp /></action><action><actionNumber>S540</actionNumber><date>4/8/2015</date><description>Amendment(s) offered</description><comment>FA1 Huffman</comment><actionTimestamp /></action><action><actionNumber>S544</actionNumber><date>4/8/2015</date><description>Amended</description><comment /><actionTimestamp /></action><action><actionNumber>S625</actionNumber><date>4/8/2015</date><description>Record vote</description><comment /><actionTimestamp /></action><action><actionNumber>S551</actionNumber><date>4/8/2015</date><description>Passed to engrossment as amended</description><comment /><actionTimestamp /></action><action><actionNumber>S625</actionNumber><date>4/8/2015</date><description>Record vote</description><comment /><actionTimestamp /></action><action><actionNumber>S507</actionNumber><date>4/9/2015</date><description>Rules suspended-Regular order of business</description><comment /><actionTimestamp /></action><action><actionNumber>S625</actionNumber><date>4/9/2015</date><description>Record vote</description><comment /><actionTimestamp /></action><action><actionNumber>S575</actionNumber><date>4/9/2015</date><description>Read 3rd time</description><comment /><actionTimestamp /></action><action><actionNumber>S540</actionNumber><date>4/9/2015</date><description>Amendment(s) offered</description><comment>FA1 Estes</comment><actionTimestamp /></action><action><actionNumber>S544</actionNumber><date>4/9/2015</date><description>Amended</description><comment /><actionTimestamp /></action><action><actionNumber>S626</actionNumber><date>4/9/2015</date><description>Vote recorded in Journal</description><comment /><actionTimestamp /></action><action><actionNumber>S577</actionNumber><date>4/9/2015</date><description>Passed as amended</description><comment /><actionTimestamp /></action><action><actionNumber>S625</actionNumber><date>4/9/2015</date><description>Record vote</description><comment /><actionTimestamp /></action><action><actionNumber>S835</actionNumber><date>4/9/2015</date><description>Reported engrossed</description><comment /><actionTimestamp /></action><action><actionNumber>H800</actionNumber><date>4/10/2015</date><description>Received from the Senate</description><comment /><actionTimestamp /></action><action><actionNumber>H005</actionNumber><date>5/14/2015</date><description>Read first time</description><comment /><actionTimestamp /></action><action><actionNumber>H063</actionNumber><date>5/14/2015</date><description>Referred to General Investigating &amp; Ethics</description><comment /><actionTimestamp>5/14/2015 12:12:00 AM</actionTimestamp></action><action><actionNumber>H201</actionNumber><date>5/19/2015</date><description>Scheduled for formal meeting on . . .</description><comment /><actionTimestamp /></action><action><actionNumber>H216</actionNumber><date>5/19/2015</date><description>Considered in formal meeting</description><comment /><actionTimestamp /></action><action><actionNumber>H241</actionNumber><date>5/19/2015</date><description>Committee substitute considered in committee</description><comment /><actionTimestamp /></action><action><actionNumber>H252</actionNumber><date>5/19/2015</date><description>Reported favorably as substituted</description><comment /><actionTimestamp /></action><action><actionNumber>H853</actionNumber><date>5/21/2015</date><description>Comte report filed with Committee Coordinator</description><comment /><actionTimestamp /></action><action><actionNumber>H855</actionNumber><date>5/21/2015</date><description>Committee report distributed</description><comment /><actionTimestamp>5/21/2015 6:14:00 PM</actionTimestamp></action><action><actionNumber>H400</actionNumber><date>5/22/2015</date><description>Committee report sent to Calendars</description><comment /><actionTimestamp /></action><action><actionNumber>H415</actionNumber><date>5/22/2015</date><description>Considered in Calendars</description><comment /><actionTimestamp /></action><action><actionNumber>H435</actionNumber><date>5/25/2015</date><description>Placed on General State Calendar</description><comment /><actionTimestamp /></action><action><actionNumber>H515</actionNumber><date>5/25/2015</date><description>Read 2nd time</description><comment /><actionTimestamp /></action><action><actionNumber>H521</actionNumber><date>5/25/2015</date><description>Postponed</description><comment>5/26/15 9:00 AM</comment><actionTimestamp /></action><action><actionNumber>H522</actionNumber><date>5/26/2015</date><description>Laid out as postponed business</description><comment /><actionTimestamp /></action><action><actionNumber>H521</actionNumber><date>5/26/2015</date><description>Postponed</description><comment>5/26/15 10:00 PM</comment><actionTimestamp /></action><action><actionNumber>H522</actionNumber><date>5/27/2015</date><description>Laid out as postponed business</description><comment /><actionTimestamp /></action><action><actionNumber>H667</actionNumber><date>5/27/2015</date><description>Point of order sustained</description><comment /><actionTimestamp /></action></actions><billtext><docTypes><bill><versions><version><versionDescription>Introduced</versionDescription><WebHTMLURL>http://www.legis.state.tx.us/tlodocs/84R/billtext/html/SB00010I.HTM</WebHTMLURL><WebPDFURL>http://www.legis.state.tx.us/tlodocs/84R/billtext/pdf/SB00010I.PDF</WebPDFURL><FTPHTMLURL>ftp://ftp.legis.state.tx.us/bills/84R/billtext/HTML/senate_bills/SB00001_SB00099/SB00010I.HTM</FTPHTMLURL><FTPPDFURL>ftp://ftp.legis.state.tx.us/bills/84R/billtext/PDF/senate_bills/SB00001_SB00099/SB00010I.PDF</FTPPDFURL></version><version><versionDescription>Senate Committee Report</versionDescription><WebHTMLURL>http://www.legis.state.tx.us/tlodocs/84R/billtext/html/SB00010S.HTM</WebHTMLURL><WebPDFURL>http://www.legis.state.tx.us/tlodocs/84R/billtext/pdf/SB00010S.PDF</WebPDFURL><FTPHTMLURL>ftp://ftp.legis.state.tx.us/bills/84R/billtext/HTML/senate_bills/SB00001_SB00099/SB00010S.HTM</FTPHTMLURL><FTPPDFURL>ftp://ftp.legis.state.tx.us/bills/84R/billtext/PDF/senate_bills/SB00001_SB00099/SB00010S.PDF</FTPPDFURL></version><version><versionDescription>Engrossed</versionDescription><WebHTMLURL>http://www.legis.state.tx.us/tlodocs/84R/billtext/html/SB00010E.HTM</WebHTMLURL><WebPDFURL>http://www.legis.state.tx.us/tlodocs/84R/billtext/pdf/SB00010E.PDF</WebPDFURL><FTPHTMLURL>ftp://ftp.legis.state.tx.us/bills/84R/billtext/HTML/senate_bills/SB00001_SB00099/SB00010E.HTM</FTPHTMLURL><FTPPDFURL>ftp://ftp.legis.state.tx.us/bills/84R/billtext/PDF/senate_bills/SB00001_SB00099/SB00010E.PDF</FTPPDFURL></version><version><versionDescription>House Committee Report</versionDescription><WebHTMLURL>http://www.legis.state.tx.us/tlodocs/84R/billtext/html/SB00010H.HTM</WebHTMLURL><WebPDFURL>http://www.legis.state.tx.us/tlodocs/84R/billtext/pdf/SB00010H.PDF</WebPDFURL><FTPHTMLURL>ftp://ftp.legis.state.tx.us/bills/84R/billtext/HTML/senate_bills/SB00001_SB00099/SB00010H.HTM</FTPHTMLURL><FTPPDFURL>ftp://ftp.legis.state.tx.us/bills/84R/billtext/PDF/senate_bills/SB00001_SB00099/SB00010H.PDF</FTPPDFURL></version></versions></bill><analysis><versions><version><versionDescription>Introduced</versionDescription><WebHTMLURL>http://www.legis.state.tx.us/tlodocs/84R/analysis/html/SB00010I.HTM</WebHTMLURL><WebPDFURL>http://www.legis.state.tx.us/tlodocs/84R/analysis/pdf/SB00010I.PDF</WebPDFURL><FTPHTMLURL>ftp://ftp.legis.state.tx.us/bills/84R/analysis/HTML/senate_bills/SB00001_SB00099/SB00010I.HTM</FTPHTMLURL><FTPPDFURL>ftp://ftp.legis.state.tx.us/bills/84R/analysis/PDF/senate_bills/SB00001_SB00099/SB00010I.PDF</FTPPDFURL></version><version><versionDescription>Senate Committee Report</versionDescription><WebHTMLURL>http://www.legis.state.tx.us/tlodocs/84R/analysis/html/SB00010S.HTM</WebHTMLURL><WebPDFURL>http://www.legis.state.tx.us/tlodocs/84R/analysis/pdf/SB00010S.PDF</WebPDFURL><FTPHTMLURL>ftp://ftp.legis.state.tx.us/bills/84R/analysis/HTML/senate_bills/SB00001_SB00099/SB00010S.HTM</FTPHTMLURL><FTPPDFURL>ftp://ftp.legis.state.tx.us/bills/84R/analysis/PDF/senate_bills/SB00001_SB00099/SB00010S.PDF</FTPPDFURL></version><version><versionDescription>House Committee Report</versionDescription><WebHTMLURL>http://www.legis.state.tx.us/tlodocs/84R/analysis/html/SB00010H.HTM</WebHTMLURL><WebPDFURL>http://www.legis.state.tx.us/tlodocs/84R/analysis/pdf/SB00010H.PDF</WebPDFURL><FTPHTMLURL>ftp://ftp.legis.state.tx.us/bills/84R/analysis/HTML/senate_bills/SB00001_SB00099/SB00010H.HTM</FTPHTMLURL><FTPPDFURL>ftp://ftp.legis.state.tx.us/bills/84R/analysis/PDF/senate_bills/SB00001_SB00099/SB00010H.PDF</FTPPDFURL></version></versions></analysis><fiscalNote><versions><version><versionDescription>Introduced</versionDescription><WebHTMLURL>http://www.legis.state.tx.us/tlodocs/84R/fiscalNotes/html/SB00010I.HTM</WebHTMLURL><WebPDFURL>http://www.legis.state.tx.us/tlodocs/84R/fiscalNotes/pdf/SB00010I.PDF</WebPDFURL><FTPHTMLURL>ftp://ftp.legis.state.tx.us/bills/84R/fiscalNotes/HTML/senate_bills/SB00001_SB00099/SB00010I.HTM</FTPHTMLURL><FTPPDFURL>ftp://ftp.legis.state.tx.us/bills/84R/fiscalNotes/PDF/senate_bills/SB00001_SB00099/SB00010I.PDF</FTPPDFURL></version><version><versionDescription>Senate Committee Report</versionDescription><WebHTMLURL>http://www.legis.state.tx.us/tlodocs/84R/fiscalNotes/html/SB00010S.HTM</WebHTMLURL><WebPDFURL>http://www.legis.state.tx.us/tlodocs/84R/fiscalNotes/pdf/SB00010S.PDF</WebPDFURL><FTPHTMLURL>ftp://ftp.legis.state.tx.us/bills/84R/fiscalNotes/HTML/senate_bills/SB00001_SB00099/SB00010S.HTM</FTPHTMLURL><FTPPDFURL>ftp://ftp.legis.state.tx.us/bills/84R/fiscalNotes/PDF/senate_bills/SB00001_SB00099/SB00010S.PDF</FTPPDFURL></version><version><versionDescription>Engrossed</versionDescription><WebHTMLURL>http://www.legis.state.tx.us/tlodocs/84R/fiscalNotes/html/SB00010E.HTM</WebHTMLURL><WebPDFURL>http://www.legis.state.tx.us/tlodocs/84R/fiscalNotes/pdf/SB00010E.PDF</WebPDFURL><FTPHTMLURL>ftp://ftp.legis.state.tx.us/bills/84R/fiscalNotes/HTML/senate_bills/SB00001_SB00099/SB00010E.HTM</FTPHTMLURL><FTPPDFURL>ftp://ftp.legis.state.tx.us/bills/84R/fiscalNotes/PDF/senate_bills/SB00001_SB00099/SB00010E.PDF</FTPPDFURL></version><version><versionDescription>House Committee Report</versionDescription><WebHTMLURL>http://www.legis.state.tx.us/tlodocs/84R/fiscalNotes/html/SB00010H.HTM</WebHTMLURL><WebPDFURL>http://www.legis.state.tx.us/tlodocs/84R/fiscalNotes/pdf/SB00010H.PDF</WebPDFURL><FTPHTMLURL>ftp://ftp.legis.state.tx.us/bills/84R/fiscalNotes/HTML/senate_bills/SB00001_SB00099/SB00010H.HTM</FTPHTMLURL><FTPPDFURL>ftp://ftp.legis.state.tx.us/bills/84R/fiscalNotes/PDF/senate_bills/SB00001_SB00099/SB00010H.PDF</FTPPDFURL></version></versions></fiscalNote></docTypes></billtext></billhistory>